universal_mcp_youtube/README.md
universal_mcp_youtube/__init__.py
universal_mcp_youtube/app.py
universal_mcp_youtube/server.py
universal_mcp_youtube-0.1.4.dist-info/METADATA
universal_mcp_youtube-0.1.4.dist-info/WHEEL
universal_mcp_youtube-0.1.4.dist-info/entry_points.txt
universal_mcp_youtube-0.1.4.dist-info/licenses/LICENSE
universal_mcp_youtube-0.1.4.dist-info/RECORD
